spicedsun/__init__.py
spicedsun/spicedsun.py
spicedsun-0.0.2.dist-info/METADATA
spicedsun-0.0.2.dist-info/WHEEL
spicedsun-0.0.2.dist-info/top_level.txt
spicedsun-0.0.2.dist-info/RECORD
