Metadata-Version: 2.1
Name: spicedsun
Version: 0.0.2
Summary: Calculation of solar data using NASA’s SPICE toolbox.
Home-page: https://github.com/GOA-UVa/spicedsun
Author: Group of Atmospheric Optics (GOA-UVa), Universidad de Valladolid
Author-email: gaton@goa.uva.es
License: UNKNOWN
Project-URL: Bug Tracker, https://github.com/GOA-UVa/spicedsun/issues
Platform: UNKNOWN
Classifier: Programming Language :: Python :: 3
Classifier: Operating System :: OS Independent
Requires-Python: >=3.7
Requires-Dist: numpy (>=1.21.5)
Requires-Dist: spiceypy (>=5.0.0)
